{
  "slug": "lawn-care-service",
  "businessName": "GreenStripe Lawn Care",
  "niche": "lawn care service",
  "layoutVariant": "route-plan",
  "tagline": "Lawn care that makes the neighbors slow down.",
  "themeSlug": "twentytwentyfive",
  "landingPage": "/",
  "palette": {
    "grass": "#1f7a3a",
    "deepGreen": "#102f1d",
    "leaf": "#8cc63f",
    "sun": "#f3c14b",
    "cream": "#f7f3e8",
    "mist": "#e7f0df",
    "soil": "#5a3b25",
    "white": "#ffffff"
  },
  "assets": {
    "hero": "assets/lawn-care/greenstripe-hero.jpg",
    "logo": "assets/lawn-care/greenstripe-logo.png",
    "favicon": "assets/lawn-care/greenstripe-favicon.png"
  },
  "assetMeta": {
    "hero": {
      "title": "GreenStripe lawn care hero image",
      "alt": "A lawn care professional trimming a crisp green front lawn."
    }
  },
  "contact": {
    "phoneLabel": "(555) 014-7883",
    "phoneHref": "tel:+15550147883",
    "email": "hello@greenstripe.test",
    "emailHref": "mailto:hello@greenstripe.test",
    "serviceArea": "Northside neighborhoods, west suburbs, and the sunny lawns in between"
  },
  "copy": {
    "eyebrow": "Local lawn care with tidy edges",
    "heroTitle": "Your lawn, minus the weekend chore.",
    "heroText": "GreenStripe keeps yards crisp, healthy, and party-ready with mowing, edging, seasonal cleanups, and friendly crews who actually close the gate.",
    "primaryCta": "Get a quick quote",
    "secondaryCta": "See services",
    "introTitle": "The grass-is-greener treatment, without the drama.",
    "introText": "We show up when we say we will, make clean work of the messy bits, and leave your yard looking like it has its life together.",
    "servicesTitle": "What we handle",
    "processTitle": "How it works",
    "proofTitle": "Neighbor-approved yard care",
    "quoteTitle": "Ready for a better-looking yard?",
    "quoteText": "Send a note with your address, yard size, and what is bugging you. We will reply with a straightforward next step."
  },
  "services": [
    {
      "title": "Weekly mowing",
      "text": "Clean cuts, fresh stripes, and reliable scheduling during peak growing season."
    },
    {
      "title": "Edges and walkways",
      "text": "Crisp borders along drives, sidewalks, beds, and patios so everything feels finished."
    },
    {
      "title": "Seasonal cleanups",
      "text": "Leaves, sticks, storm debris, and the mysterious corner pile finally meet their match."
    }
  ],
  "process": [
    {
      "title": "Snap a few photos",
      "text": "Send the lawn, trouble spots, and the best way to access the yard."
    },
    {
      "title": "Get a clear plan",
      "text": "We recommend a cadence, scope, and price without making it weird."
    },
    {
      "title": "Enjoy the view",
      "text": "We keep the schedule moving and the curb appeal doing its little victory lap."
    }
  ],
  "proof": [
    {
      "stat": "24-hour",
      "label": "quote follow-up on weekdays"
    },
    {
      "stat": "3-season",
      "label": "mowing, cleanup, and refresh plans"
    },
    {
      "stat": "Gate-check",
      "label": "crew checklist after every visit"
    }
  ],
  "release": {
    "status": "approved",
    "reviewedAt": "2026-06-24",
    "visualBaseline": "pending",
    "reviewChecklist": {
      "firstViewportClear": true,
      "logoReadable": true,
      "layoutDistinct": true,
      "ctaClear": true,
      "copySpecific": true,
      "noImageArtifacts": true,
      "heroArtDirected": true,
      "hierarchyDistinct": true,
      "signatureMove": true,
      "restrainedComposition": true,
      "screenshotCompared": true
    }
  }
}
